web_assets_downloader/__init__.py
web_assets_downloader/web_assets_downloader.py
web_assets_downloader-2.3.1.dist-info/METADATA
web_assets_downloader-2.3.1.dist-info/WHEEL
web_assets_downloader-2.3.1.dist-info/dependency_links.txt
web_assets_downloader-2.3.1.dist-info/entry_points.txt
web_assets_downloader-2.3.1.dist-info/top_level.txt
web_assets_downloader-2.3.1.dist-info/RECORD
