Metadata-Version: 2.1
Name: web-assets-downloader
Version: 2.3.1
Summary: A package for downloading web content and assets
Home-page: https://github.com/arif-x/web-assets-downloader
Author: Ariffudin
Author-email: sudo.ariffudin@email.com
License: MIT
Project-URL: Source, https://github.com/arif-x/web-assets-downloader
Project-URL: Source Code, https://github.com/arif-x/web-assets-downloader
Keywords: web downloader requests BeautifulSoup
Platform: UNKNOWN
Classifier: License :: OSI Approved :: MIT License
Classifier: Programming Language :: Python :: 3
Classifier: Programming Language :: Python :: 3.6
Classifier: Programming Language :: Python :: 3.7
Classifier: Programming Language :: Python :: 3.8
Classifier: Programming Language :: Python :: 3.9
Classifier: Programming Language :: Python :: 3.10
Classifier: Operating System :: OS Independent
Requires-Dist: PyPDF2
Requires-Dist: beautifulsoup4
Requires-Dist: openpyxl
Requires-Dist: pillow
Requires-Dist: python-docx
Requires-Dist: requests
